{"stats":{"minecraft:custom":{"minecraft:jump":161,"minecraft:time_since_rest":15828,"minecraft:damage_dealt":113,"minecraft:crouch_one_cm":5016,"minecraft:damage_taken":95,"minecraft:sprint_one_cm":516,"minecraft:play_time":15828,"minecraft:time_since_death":15828,"minecraft:walk_one_cm":24924,"minecraft:sneak_time":1383,"minecraft:total_world_time":15828,"minecraft:fall_one_cm":4427,"minecraft:fly_one_cm":3104,"minecraft:player_kills":1},"minecraft:used":{"alexsmobs:animal_dictionary":3}},"DataVersion":3465}